setup.py
cms_facebook/__init__.py
cms_facebook/cms_plugins.py
cms_facebook/models.py
cms_facebook/migrations/0001_initial.py
cms_facebook/migrations/__init__.py
django_cms_fakebook.egg-info/PKG-INFO
django_cms_fakebook.egg-info/SOURCES.txt
django_cms_fakebook.egg-info/dependency_links.txt
django_cms_fakebook.egg-info/not-zip-safe
django_cms_fakebook.egg-info/top_level.txt