Metadata-Version: 1.0
Name: django-cms-fakebook
Version: 0.1.0
Summary: Django CMS Facebook Plugins
Home-page: http://github.com/ojii/django-cms-facebook
Author: Jonas Obrist
Author-email: jonas.obrist@divio.ch
License: UNKNOWN
Platform: UNKNOWN
